copula/pyCopula.py
copula-0.0.4.dist-info/LICENSE
copula-0.0.4.dist-info/METADATA
copula-0.0.4.dist-info/WHEEL
copula-0.0.4.dist-info/top_level.txt
copula-0.0.4.dist-info/RECORD
