Metadata-Version: 2.1
Name: copula
Version: 0.0.4
Summary: A python library for sampling and generating new Data points by multivariate Gaussian copulas.
Home-page: https://github.com/ashiq24/Copula
Author: Md Ashiqur Rahman
Author-email: ashiqbuet14@gmail.com
License: UNKNOWN
Platform: UNKNOWN
Classifier: Programming Language :: Python :: 3
Classifier: License :: OSI Approved :: MIT License
Classifier: Operating System :: OS Independent
